fonemas/__init__.py
fonemas/fonemas.py
fonemas-2.1.0.dist-info/LICENCE
fonemas-2.1.0.dist-info/METADATA
fonemas-2.1.0.dist-info/WHEEL
fonemas-2.1.0.dist-info/top_level.txt
fonemas-2.1.0.dist-info/RECORD
