Metadata-Version: 2.1
Name: fonemas
Version: 2.1.0
Summary: Phonetic transcription of Spanish
Home-page: https://github.com/fsanzl/fonemas
Author: Fernando Sanz-Lázaro
Author-email: fsanzl@gmail.com
License: LGPL
Project-URL: Source, https://github.com/fsanzl/fonemas/
Project-URL: Tracker, https://github.com/fsanzl/fonemas/issues
Classifier: License :: OSI Approved :: GNU Lesser General Public License v2 or later (LGPLv2+)
Classifier: Programming Language :: Python :: 3
Classifier: Programming Language :: Python :: 3.10
Classifier: Programming Language :: Python :: 3.11
Classifier: Programming Language :: Python :: 3.9
Classifier: Programming Language :: Python :: 3.8
Classifier: Programming Language :: Python :: 3.7
Classifier: Programming Language :: Python :: 3.6
Classifier: Natural Language :: Spanish
Requires-Python: >=3.6
License-File: LICENCE
Requires-Dist: silabeador
